[
  {
    "id": 1,
    "image": "",
    "name": "Neel Patel",
    "title": "Founder & CTO"
  },
  {
    "id": 2,
    "image": "",
    "name": "Aman Patel",
    "title": "BDE"
  },
  {
    "id": 3,
    "image": "",
    "name": "Dhansukh",
    "title": "React developer"
  },
  {
    "id": 7,
    "image": "",
    "name": "Yash Jani",
    "title": "Node.js devloper"
  },
  {
    "id": 4,
    "image": "",
    "name": " Priyanka Maneria",
    "title": "Jr. Developer"
  },
  {
    "id": 5,
    "image": "",
    "name": "Ayushya Patel",
    "title": "Jr. Developer"
  },
  {
    "id": 6,
    "image": "",
    "name": "Ashvini Parmar",
    "title": "UI/UX designer"
  },
  {
    "id": 6,
    "image": "/img/team/5.jpg",
    "name": "Yash Jani",
    "title": "Backend Developer"
  }
]
